docx_parser/__init__.py
docx_parser/version.json
docx_parser/bin/__init__.py
docx_parser/bin/main.py
docx_parser/core/__init__.py
docx_parser/core/parser.py
docx_parser/util/__init__.py
docx_parser-1.0.3.dist-info/METADATA
docx_parser-1.0.3.dist-info/WHEEL
docx_parser-1.0.3.dist-info/entry_points.txt
docx_parser-1.0.3.dist-info/top_level.txt
docx_parser-1.0.3.dist-info/RECORD
