Metadata-Version: 2.4
Name: docx_parser
Version: 1.0.3
Summary: parse all contents of a docx file with python-docx
Home-page: https://github.com/suqingdong/docx_parser
Author: suqingdong
Author-email: suqingdong1114@gmail.com
License: BSD License
Classifier: Development Status :: 5 - Production/Stable
Classifier: Operating System :: OS Independent
Classifier: Intended Audience :: Developers
Classifier: Programming Language :: Python
Classifier: Programming Language :: Python :: 3
Classifier: Programming Language :: Python :: 3.8
Classifier: Programming Language :: Python :: 3.9
Classifier: Topic :: Software Development :: Libraries
Requires-Dist: click
Requires-Dist: pillow
Requires-Dist: python-docx
Dynamic: author
Dynamic: author-email
Dynamic: classifier
Dynamic: description
Dynamic: description-content-type
Dynamic: home-page
Dynamic: license
Dynamic: requires-dist
Dynamic: summary
